i2a/__init__.py
i2a/colors.py
i2a/i2a.py
i2a-1.3.dist-info/DESCRIPTION.rst
i2a-1.3.dist-info/METADATA
i2a-1.3.dist-info/RECORD
i2a-1.3.dist-info/WHEEL
i2a-1.3.dist-info/entry_points.txt
i2a-1.3.dist-info/metadata.json
i2a-1.3.dist-info/top_level.txt
