Metadata-Version: 2.0
Name: i2a
Version: 1.3
Summary: i2a creates ASCII art from images right on your terminal.
Home-page: http://github.com/mavidser/i2a
Author: Sid Verma
Author-email: sid@sidverma.net
License: MIT
Keywords: image,jpg,ascii,art
Platform: UNKNOWN
Requires-Dist: Pillow (>=2.5.0)
Requires-Dist: docopt (>=0.6.2)
